metaapi_cloud_sdk/__init__.py
metaapi_cloud_sdk/logger.py
metaapi_cloud_sdk/clients/__init__.py
metaapi_cloud_sdk/clients/domain_client.py
metaapi_cloud_sdk/clients/error_handler.py
metaapi_cloud_sdk/clients/http_client.py
metaapi_cloud_sdk/clients/metaapi_client.py
metaapi_cloud_sdk/clients/method_access_exception.py
metaapi_cloud_sdk/clients/options_validator.py
metaapi_cloud_sdk/clients/timeout_exception.py
metaapi_cloud_sdk/clients/metaapi/__init__.py
metaapi_cloud_sdk/clients/metaapi/client_api_client.py
metaapi_cloud_sdk/clients/metaapi/expert_advisor_client.py
metaapi_cloud_sdk/clients/metaapi/historical_market_data_client.py
metaapi_cloud_sdk/clients/metaapi/latency_listener.py
metaapi_cloud_sdk/clients/metaapi/latency_service.py
metaapi_cloud_sdk/clients/metaapi/metaapi_websocket_client.py
metaapi_cloud_sdk/clients/metaapi/metatrader_account_client.py
metaapi_cloud_sdk/clients/metaapi/metatrader_account_generator_client.py
metaapi_cloud_sdk/clients/metaapi/not_connected_exception.py
metaapi_cloud_sdk/clients/metaapi/not_synchronized_exception.py
metaapi_cloud_sdk/clients/metaapi/packet_logger.py
metaapi_cloud_sdk/clients/metaapi/packet_orderer.py
metaapi_cloud_sdk/clients/metaapi/provisioning_profile_client.py
metaapi_cloud_sdk/clients/metaapi/reconnect_listener.py
metaapi_cloud_sdk/clients/metaapi/subscription_manager.py
metaapi_cloud_sdk/clients/metaapi/synchronization_listener.py
metaapi_cloud_sdk/clients/metaapi/synchronization_throttler.py
metaapi_cloud_sdk/clients/metaapi/token_management_client.py
metaapi_cloud_sdk/clients/metaapi/trade_exception.py
metaapi_cloud_sdk/integration_tests/__init__.py
metaapi_cloud_sdk/metaapi/__init__.py
metaapi_cloud_sdk/metaapi/connection_health_monitor.py
metaapi_cloud_sdk/metaapi/connection_registry.py
metaapi_cloud_sdk/metaapi/connection_registry_model.py
metaapi_cloud_sdk/metaapi/expert_advisor.py
metaapi_cloud_sdk/metaapi/filesystem_history_database.py
metaapi_cloud_sdk/metaapi/history_items_memory_storage.py
metaapi_cloud_sdk-29.0.0.dist-info/licenses/LICENSE
metaapi_cloud_sdk-29.0.0.dist-info/METADATA
metaapi_cloud_sdk-29.0.0.dist-info/WHEEL
metaapi_cloud_sdk-29.0.0.dist-info/top_level.txt
metaapi_cloud_sdk-29.0.0.dist-info/RECORD
