Metadata-Version: 2.4
Name: metaapi_cloud_sdk
Version: 29.0.0
Summary: SDK for MetaApi, a professional cloud forex API which includes MetaTrader REST API and MetaTrader websocket API. Supports both MetaTrader 5 (MT5) and MetaTrader 4 (MT4). CopyFactory copy trading API included. (https://metaapi.cloud)
Author-email: MetaApi <support@metaapi.cloud>
License: (c) Copyright 2020-2023 MetaApi DMCC. All rights reserved
Project-URL: Homepage, https://github.com/metaapi/metaapi-python-sdk
Keywords: metaapi.cloud,MetaTrader,MetaTrader 5,MetaTrader 4,MetaTrader5,MetaTrader4,MT,MT4,MT5,forex,trading,API,REST,websocket,client,sdk,cloud,free,copy trading,copytrade,copy trade,trade copying
Classifier: Programming Language :: Python :: 3
Classifier: License :: Other/Proprietary License
Classifier: Operating System :: OS Independent
Requires-Python: >=3.8
License-File: LICENSE
Requires-Dist: aiohttp>=3.7.4
Requires-Dist: python-engineio<4.0.0,>=3.14.2
Requires-Dist: typing-extensions>=4.0.0
Requires-Dist: iso8601
Requires-Dist: pytz
Requires-Dist: python-socketio[asyncio_client]<5.0.0,>=4.6.0
Requires-Dist: requests>=2.28.0
Requires-Dist: httpx<0.29.0,>=0.28.0
Requires-Dist: metaapi-cloud-copyfactory-sdk<13.0.0,>=12.0.0
Requires-Dist: metaapi-cloud-metastats-sdk<7.0.0,>=6.0.0
Requires-Dist: rapidfuzz
Provides-Extra: test
Requires-Dist: pytest==6.2.5; extra == "test"
Requires-Dist: pytest-mock==3.8.2; extra == "test"
Requires-Dist: pytest-asyncio==0.16.0; extra == "test"
Requires-Dist: asynctest==0.13.0; extra == "test"
Requires-Dist: mock==4.0.3; extra == "test"
Requires-Dist: freezegun==1.0.0; extra == "test"
Requires-Dist: respx==0.22.0; extra == "test"
Dynamic: license-file
